beespy/__init__.py
beespy/api.py
beespy-0.0.1.dist-info/METADATA
beespy-0.0.1.dist-info/WHEEL
beespy-0.0.1.dist-info/top_level.txt
beespy-0.0.1.dist-info/RECORD
