Metadata-Version: 2.1
Name: beespy
Version: 0.0.1
Summary: This class provides methodes for using BeeSpy API
Home-page: UNKNOWN
Author: Andreas Ziegler, Benjamin Dollinger
Author-email: ziegler.andi@icloud.com
License: MIT
Platform: UNKNOWN
